[{
  "_id": {
    "$oid": "5ede6a82fed78043ac0339fa"
  },
  "title": "Todo 1",
  "description": "Todo 1 description",
  "createdAt": "2020-01-01",
  "updatedAt": "2020-04-04",
  "status": "open",
  "deadline": "2020-06-12T20:18",
  "categoryId": "5ede6bbafed78043ac0339ff"
},{
  "_id": {
    "$oid": "5ede6a82fed78043ac0339fb"
  },
  "title": "Todo 2",
  "description": "Todo 2 description",
  "createdAt": "2020-01-01",
  "updatedAt": "2020-04-04",
  "status": "open",
  "deadline": "2020-06-12T20:18",
  "categoryId": "5ede6bbafed78043ac0339ff"
},{
  "_id": {
    "$oid": "5ede6a82fed78043ac0339fc"
  },
  "title": "Todo 3",
  "description": "Todo 3 description",
  "createdAt": "2020-01-01",
  "updatedAt": "2020-04-04",
  "status": "open",
  "deadline": "2020-06-12T20:18",
  "categoryId": "5ede6bbafed78043ac033a00"
},{
  "_id": {
    "$oid": "5ede6a82fed78043ac0339fe"
  },
  "title": "Todo 4",
  "description": "Todo 4 description",
  "createdAt": "2020-01-01",
  "updatedAt": "2020-04-04",
  "status": "open",
  "deadline": "2020-06-12T20:18",
  "categoryId": "5ede6bbafed78043ac033a01"
},{
  "_id": {
    "$oid": "5ede7ef02ef0cd3c1c8660e8"
  },
  "title": "Todo 5",
  "description": "Todo 5 description",
  "createdAt": "2020-01-01",
  "updatedAt": "2020-04-04",
  "status": "open",
  "deadline": "2020-06-12T20:18",
  "categoryId": "5ede6bbafed78043ac033a00"
}]